[
    {
        "id": "penang-fried-kuey-teow",
        "state": "Penang",
        "name": "Penang Fried Kuey Teow",
        "thumb": "../image/penangkhewtiao.jpg",
        "desc": "Flat rice noodles stir-fried over high heat with a savory blend of soy sauce",
        "tags": [
            "noodle"
        ]
    },
    {
        "id": "penang-hokkien-mee",
        "state": "Penang",
        "name": "Penang Hokkien Mee",
        "thumb": "../image/Penang-Prawn-Mee-Wide.jpg",
        "desc": "Vibrant noodle soup renowned for its intensely flavorful and spicy broth",
        "tags": [
            "noodle",
            "spicy"
        ]
    },
    {
        "id": "penang-yam-rice",
        "state": "Penang",
        "name": "Yam Rice",
        "thumb": "../image/YamRice.jpg",
        "desc": "Rice cooked with diced yam (taro)",
        "tags": [
            "taro",
            "rice"
        ]
    },
    {
        "id": "penang-rojak",
        "state": "Penang",
        "name": "Rojak",
        "thumb": "../image/rojak.jpg",
        "desc": "Rice cooked with diced yam (taro)",
        "tags": [
            "taro",
            "rice"
        ]
    },
    {
        "id": "Perak-bean-sprout-chicken",
        "state": "Perak",
        "name": "Bean Sprout Chicken",
        "thumb": "../image/chicken.jpg",
        "desc": "poached chicken and crunchy bean sprouts with a soy sauce and sesame oil",
        "tags": [
            "sesame oil",
            "chicken"
        ]
    },
    {
        "id": "perak-chee-cheong-fun",
        "state": "Perak",
        "name": "Chee Cheong Fun",
        "thumb": "../image/Chee.jpg",
        "desc": "Silky, thicker noodles served with a variety of sauces",
        "tags": [
            "noodle",
            "curry"
        ]
    },
    {
        "id": "perak-curry-chicken-bread",
        "state": "Perak",
        "name": "Curry Chicken Bread",
        "thumb": "../image/currychickenbread.jpg",
        "desc": "Chicken curry baked within a large, soft and slightly sweet bread loaf",
        "tags": [
            "bread",
            "curry",
            "chicken"
        ]
    },
    {
        "id": "Perak-shredded-chicken-hor-fun",
        "state": "Perak",
        "name": "Shredded Chicken Hor Fun",
        "thumb": "../image/ShreddedChickenKueyTeow.jpg",
        "desc": "Silky flat rice noodles",
        "tags": [
            "chicken",
            "noodle"
        ]
    },
    {
        "id": "sarawak-kampua",
        "state": "Sarawak",
        "name": "Kampua",
        "thumb": "../image/kampua1.jpg",
        "desc": "Straight egg noodles tossed in a simple yet flavorful sauce",
        "tags": [
            "non-halal",
            "noodle"
        ]
    },
    {
        "id": "sarawak-kompyang",
        "state": "Sarawak",
        "name": "Kompyang",
        "thumb": "../image/gongbia.jpg",
        "desc": "Traditional baked bread with a savory minced pork filling",
        "tags": [
            "non-halal",
            "bread"
        ]
    },
    {
        "id": "sarawak-wok-rice-paste-with-soup",
        "state": "Sarawak",
        "name": "Ding Bian Hu",
        "thumb": "../image/FoochowDelicacies.jpg",
        "desc": "Foochow dish with broth is made from a pork and cuttlefish stock",
        "tags": [
            "non-halal",
            "noodle"
        ]
    },
    {
        "id": "sarawak-laksa",
        "state": "Sarawak",
        "name": "Sarawak Laksa",
        "thumb": "../image/laksa.jpg",
        "desc": "Noodle soup from the state of Sarawak",
        "tags": [
            "spicy",
            "noodle"
        ]
    },
    {
        "id": "melaka-chicken-rice-ball",
        "state": "Melaka",
        "name": "Melaka Chicken Rice Ball",
        "thumb": "../image/ChickenRiceBallThumbnail.jpg",
        "desc": "Fragrant chicken-flavored rice is hand-rolled into compact, bite-sized balls",
        "tags": [
            "ball",
            "rice"
        ]
    },
    {
        "id": "melaka-cendol",
        "state": "Melaka",
        "name": "Cendol",
        "thumb": "../image/cendol1.jpg",
        "desc": "Refreshing Malaysian dessert",
        "tags": [
            "snack",
            "sweet"
        ]
    },
    {
        "id": "mmelaka-pork-lard-popiah",
        "state": "Melaka",
        "name": "Pork Lard Popiah",
        "thumb": "../image/porklardpopiah.jpg",
        "desc": "Spring roll from Melaka",
        "tags": [
            "pork",
            "non-halal"
        ]
    },
    {
        "id": "mmelaka-satay",
        "state": "Melaka",
        "name": "Satay",
        "thumb": "../image/satay.jpg",
        "desc": "Marinated pork or chicken skewers grilled over charcoal",
        "tags": [
            "pork",
            "chicken"
        ]
    }
]